{
  "district_id": 4,
  "constituency": "Castries East",
  "candidates": [
    {
      "name": "CHICOT",
      "party": "UWP"
    },
    {
      "name": "PIERRE",
      "party": "SLP"
    }
  ],
  "divisions": {
    "D1": {
      "name": "BOCAGE SECONDARY SCHOOL",
      "buckets": [
        {
          "range": "A-G",
          "electors": 461,
          "votes": [
            0,
            0
          ],
          "rejected": 0,
          "votes_cast": 0
        },
        {
          "range": "H-M",
          "electors": 359,
          "votes": [
            0,
            0
          ],
          "rejected": 0,
          "votes_cast": 0
        },
        {
          "range": "N-Z",
          "electors": 314,
          "votes": [
            0,
            0
          ],
          "rejected": 0,
          "votes_cast": 0
        }
      ],
      "electors": 1134,
      "votes_cast": 0,
      "is_counted": false,
      "votes_remaining": 1134,
      "buckets_total": 3,
      "buckets_counted": 0
    },
    "D2": {
      "name": "ENTREPOT SECONDARY SCHOOL",
      "buckets": [
        {
          "range": "A-B",
          "electors": 435,
          "votes": [
            0,
            0
          ],
          "rejected": 0,
          "votes_cast": 0
        },
        {
          "range": "C-D",
          "electors": 468,
          "votes": [
            0,
            0
          ],
          "rejected": 0,
          "votes_cast": 0
        },
        {
          "range": "E-F",
          "electors": 490,
          "votes": [
            0,
            0
          ],
          "rejected": 0,
          "votes_cast": 0
        },
        {
          "range": "G-I",
          "electors": 390,
          "votes": [
            0,
            0
          ],
          "rejected": 0,
          "votes_cast": 0
        },
        {
          "range": "J-K",
          "electors": 427,
          "votes": [
            0,
            0
          ],
          "rejected": 0,
          "votes_cast": 0
        },
        {
          "range": "L-MAY",
          "electors": 384,
          "votes": [
            0,
            0
          ],
          "rejected": 0,
          "votes_cast": 0
        },
        {
          "range": "MC-P",
          "electors": 447,
          "votes": [
            0,
            0
          ],
          "rejected": 0,
          "votes_cast": 0
        },
        {
          "range": "Q-S",
          "electors": 424,
          "votes": [
            0,
            0
          ],
          "rejected": 0,
          "votes_cast": 0
        },
        {
          "range": "T-Z",
          "electors": 282,
          "votes": [
            0,
            0
          ],
          "rejected": 0,
          "votes_cast": 0
        }
      ],
      "electors": 3747,
      "votes_cast": 0,
      "is_counted": false,
      "votes_remaining": 3747,
      "buckets_total": 9,
      "buckets_counted": 0
    },
    "D3": {
      "name": "MARCHAND PARISH CENTRE",
      "buckets": [
        {
          "range": "A-J",
          "electors": 358,
          "votes": [
            0,
            0
          ],
          "rejected": 0,
          "votes_cast": 0
        },
        {
          "range": "K-Z",
          "electors": 397,
          "votes": [
            0,
            0
          ],
          "rejected": 0,
          "votes_cast": 0
        }
      ],
      "electors": 755,
      "votes_cast": 0,
      "is_counted": false,
      "votes_remaining": 755,
      "buckets_total": 2,
      "buckets_counted": 0
    },
    "D4": {
      "name": "BISHOP CHARLES GARCHET R.C. COMBINED SCHOOL",
      "buckets": [
        {
          "range": "B-C",
          "electors": 502,
          "votes": [
            0,
            0
          ],
          "rejected": 0,
          "votes_cast": 0
        },
        {
          "range": "D-E",
          "electors": 410,
          "votes": [
            0,
            0
          ],
          "rejected": 0,
          "votes_cast": 0
        },
        {
          "range": "F-G",
          "electors": 485,
          "votes": [
            0,
            0
          ],
          "rejected": 0,
          "votes_cast": 0
        },
        {
          "range": "H-JN",
          "electors": 419,
          "votes": [
            0,
            0
          ],
          "rejected": 0,
          "votes_cast": 0
        },
        {
          "range": "JOH-L",
          "electors": 507,
          "votes": [
            0,
            0
          ],
          "rejected": 0,
          "votes_cast": 0
        },
        {
          "range": "M-O",
          "electors": 332,
          "votes": [
            0,
            0
          ],
          "rejected": 0,
          "votes_cast": 0
        },
        {
          "range": "P-R",
          "electors": 352,
          "votes": [
            0,
            0
          ],
          "rejected": 0,
          "votes_cast": 0
        },
        {
          "range": "T-Z",
          "electors": 223,
          "votes": [
            0,
            0
          ],
          "rejected": 0,
          "votes_cast": 0
        }
      ],
      "electors": 3230,
      "votes_cast": 0,
      "is_counted": false,
      "votes_remaining": 3230,
      "buckets_total": 8,
      "buckets_counted": 0
    },
    "D5(a)": {
      "name": "PLAYERS PAVILLION, MINDOO PHILLIP PARK",
      "buckets": [
        {
          "range": "A-C",
          "electors": 472,
          "votes": [
            0,
            0
          ],
          "rejected": 0,
          "votes_cast": 0
        },
        {
          "range": "D-F",
          "electors": 432,
          "votes": [
            0,
            0
          ],
          "rejected": 0,
          "votes_cast": 0
        },
        {
          "range": "G-J",
          "electors": 456,
          "votes": [
            0,
            0
          ],
          "rejected": 0,
          "votes_cast": 0
        }
      ],
      "electors": 1360,
      "votes_cast": 0,
      "is_counted": false,
      "votes_remaining": 1360,
      "buckets_total": 3,
      "buckets_counted": 0
    },
    "D5(b)": {
      "name": "PAN-SHED, BELGRAVE COURT, MARCHAND GROUNDS",
      "buckets": [
        {
          "range": "K-O",
          "electors": 352,
          "votes": [
            0,
            0
          ],
          "rejected": 0,
          "votes_cast": 0
        },
        {
          "range": "P-SP",
          "electors": 314,
          "votes": [
            0,
            0
          ],
          "rejected": 0,
          "votes_cast": 0
        },
        {
          "range": "ST-Z",
          "electors": 237,
          "votes": [
            0,
            0
          ],
          "rejected": 0,
          "votes_cast": 0
        }
      ],
      "electors": 903,
      "votes_cast": 0,
      "is_counted": false,
      "votes_remaining": 903,
      "buckets_total": 3,
      "buckets_counted": 0
    },
    "D6": {
      "name": "DU BOULAY BUILDING",
      "buckets": [
        {
          "range": "A-G",
          "electors": 407,
          "votes": [
            0,
            0
          ],
          "rejected": 0,
          "votes_cast": 0
        },
        {
          "range": "H-M",
          "electors": 324,
          "votes": [
            0,
            0
          ],
          "rejected": 0,
          "votes_cast": 0
        },
        {
          "range": "N-Z",
          "electors": 282,
          "votes": [
            0,
            0
          ],
          "rejected": 0,
          "votes_cast": 0
        }
      ],
      "electors": 1013,
      "votes_cast": 0,
      "is_counted": false,
      "votes_remaining": 1013,
      "buckets_total": 3,
      "buckets_counted": 0
    }
  },
  "total_electors": 12142,
  "total_votes_cast": 0,
  "total_polling_divisions": 7,
  "polling_divisions_counted": 0,
  "polling_divisions_remaining": 7,
  "counted_divisions": [],
  "uncounted_divisions": [
    "D1",
    "D2",
    "D3",
    "D4",
    "D5(a)",
    "D5(b)",
    "D6"
  ],
  "total_ballot_boxes": 31,
  "ballot_boxes_counted": 0,
  "ballot_boxes_remaining": 31,
  "counted_ballot_boxes": [],
  "uncounted_ballot_boxes": [
    "D1:A-G",
    "D1:H-M",
    "D1:N-Z",
    "D2:A-B",
    "D2:C-D",
    "D2:E-F",
    "D2:G-I",
    "D2:J-K",
    "D2:L-MAY",
    "D2:MC-P",
    "D2:Q-S",
    "D2:T-Z",
    "D3:A-J",
    "D3:K-Z",
    "D4:B-C",
    "D4:D-E",
    "D4:F-G",
    "D4:H-JN",
    "D4:JOH-L",
    "D4:M-O",
    "D4:P-R",
    "D4:T-Z",
    "D5(a):A-C",
    "D5(a):D-F",
    "D5(a):G-J",
    "D5(b):K-O",
    "D5(b):P-SP",
    "D5(b):ST-Z",
    "D6:A-G",
    "D6:H-M",
    "D6:N-Z"
  ],
  "votes_remaining": 12142
}